CHANGES.txt
LICENSE.txt
MANIFEST.in
README.rst
setup.py
bin/ttrack
lib/tracklib.py
lib/ttrack.egg-info/PKG-INFO
lib/ttrack.egg-info/SOURCES.txt
lib/ttrack.egg-info/dependency_links.txt
lib/ttrack.egg-info/requires.txt
lib/ttrack.egg-info/top_level.txt
test/test_tracklib.py