Metadata-Version: 1.0
Name: ttrack
Version: 1.0.0
Summary: Command-line time tracking utility
Home-page: https://github.com/Cartroo/ttrack
Author: Andy Pearce
Author-email: andy@andy-pearce.com
License: LICENSE.txt
Platform: UNKNOWN
